anglefadez/__init__.py
anglefadez/fade.py
anglefadez-0.1.0.dist-info/LICENSE
anglefadez-0.1.0.dist-info/METADATA
anglefadez-0.1.0.dist-info/WHEEL
anglefadez-0.1.0.dist-info/top_level.txt
anglefadez-0.1.0.dist-info/RECORD
