Metadata-Version: 2.1
Name: anglefadez
Version: 0.1.0
Summary: Cool terminal text fade.
Author: Angle Facts
Author-email: your@email.com
Classifier: Programming Language :: Python :: 3
Classifier: Operating System :: OS Independent
Classifier: Intended Audience :: Developers
Classifier: License :: OSI Approved :: MIT License
Requires-Python: >=3.6
License-File: LICENSE
